iflow_mcp_mcp_think_tool-0.1.0.dist-info/licenses/LICENSE
think_tool/__init__.py
think_tool/server.py
iflow_mcp_mcp_think_tool-0.1.0.dist-info/METADATA
iflow_mcp_mcp_think_tool-0.1.0.dist-info/WHEEL
iflow_mcp_mcp_think_tool-0.1.0.dist-info/entry_points.txt
iflow_mcp_mcp_think_tool-0.1.0.dist-info/top_level.txt
iflow_mcp_mcp_think_tool-0.1.0.dist-info/RECORD
