Metadata-Version: 2.4
Name: iflow-mcp_mcp-think-tool
Version: 0.1.0
Summary: An MCP server implementing the think tool for Claude and other LLMs
Home-page: https://github.com/yourusername/mcp-think-tool
Author: Your Name
Author-email: Your Name <your.email@example.com>
Requires-Python: >=3.10
License-File: LICENSE
Requires-Dist: mcp>=1.2.0
Dynamic: author
Dynamic: home-page
Dynamic: license-file
Dynamic: requires-python
